flet/__init__.py
flet/__pyinstaller/__init__.py
flet/__pyinstaller/config.py
flet/__pyinstaller/hook-flet.py
flet/__pyinstaller/macos_utils.py
flet/__pyinstaller/rthooks/pyi_rth_localhost_fletd.py
flet/__pyinstaller/rthooks.dat
flet/__pyinstaller/utils.py
flet/__pyinstaller/win_utils.py
flet/async_local_socket_connection.py
flet/async_websocket_connection.py
flet/auth/authorization.py
flet/auth/group.py
flet/auth/oauth_provider.py
flet/auth/oauth_token.py
flet/auth/providers/auth0_oauth_provider.py
flet/auth/providers/azure_oauth_provider.py
flet/auth/providers/github_oauth_provider.py
flet/auth/providers/google_oauth_provider.py
flet/auth/user.py
flet/cli/cli.py
flet/cli/commands/base.py
flet/cli/commands/options.py
flet/cli/commands/pack.py
flet/cli/commands/publish.py
flet/cli/commands/run.py
flet/constants.py
flet/flet.py
flet/matplotlib_chart.py
flet/plotly_chart.py
flet/pubsub.py
flet/reconnecting_websocket.py
flet/security.py
flet/sync_local_socket_connection.py
flet/sync_websocket_connection.py
flet/utils.py
flet/version.py
robocorp_flet-0.4.2.3.dist-info/METADATA
robocorp_flet-0.4.2.3.dist-info/WHEEL
robocorp_flet-0.4.2.3.dist-info/entry_points.txt
robocorp_flet-0.4.2.3.dist-info/RECORD
