Metadata-Version: 2.1
Name: robocorp-flet
Version: 0.4.2.3
Summary: Flet for Python - easily build interactive multi-platform apps in Python
License: Apache-2.0
Author: Appveyor Systems Inc.
Author-email: hello@flet.dev
Requires-Python: >=3.7,<4.0
Classifier: License :: OSI Approved :: Apache Software License
Classifier: Programming Language :: Python :: 3
Classifier: Programming Language :: Python :: 3.7
Classifier: Programming Language :: Python :: 3.8
Classifier: Programming Language :: Python :: 3.9
Classifier: Programming Language :: Python :: 3.10
Classifier: Programming Language :: Python :: 3.11
Requires-Dist: httpx (>=0.23.3,<0.24.0)
Requires-Dist: oauthlib (>=3.2.2,<4.0.0)
Requires-Dist: packaging (>=23)
Requires-Dist: robocorp-flet-core (==0.4.2)
Requires-Dist: typing-extensions (>=4.4.0,<5.0.0) ; python_version < "3.8"
Requires-Dist: watchdog (>=2.2.1,<3.0.0)
Requires-Dist: websocket-client (>=1.4.2,<2.0.0)
Requires-Dist: websockets (>=10.4,<11.0)
Project-URL: documentation, https://flet.dev/docs
Project-URL: homepage, https://flet.dev
Project-URL: repository, https://github.com/flet-dev/flet
